reliability_metrics/__init__.py
reliability_metrics/calculator.py
reliability_metrics/utils.py
reliability_metrics-0.1.4.dist-info/METADATA
reliability_metrics-0.1.4.dist-info/WHEEL
reliability_metrics-0.1.4.dist-info/top_level.txt
reliability_metrics-0.1.4.dist-info/RECORD
