Metadata-Version: 2.4
Name: reliability-metrics
Version: 0.1.4
Summary: Compute hardware reliability and service metrics easily from shipment and return data.
Home-page: https://github.com/yourgithub/reliability-metrics
Author: YOUR NAME
Author-email: YOUR NAME <your.email@example.com>
Requires-Python: >=3.7
Requires-Dist: pandas
